[{"month":"2021-05-01","deals":14,"median_unit_price_ping":191330.5713375,"avg_unit_price_ping":196862.802535,"median_total_price":5425000.0},{"month":"2021-06-01","deals":13,"median_unit_price_ping":191305.77795000002,"avg_unit_price_ping":196093.06321230766,"median_total_price":5550000.0},{"month":"2021-07-01","deals":2,"median_unit_price_ping":205441.31461,"avg_unit_price_ping":205441.31461,"median_total_price":9760000.0},{"month":"2021-08-01","deals":1,"median_unit_price_ping":211738.83503500003,"avg_unit_price_ping":211738.83503500003,"median_total_price":5860000.0},{"month":"2021-09-01","deals":3,"median_unit_price_ping":207041.31455,"avg_unit_price_ping":176765.83359166668,"median_total_price":6393600.0},{"month":"2021-10-01","deals":6,"median_unit_price_ping":206447.92614250001,"avg_unit_price_ping":162542.14266500002,"median_total_price":5640000.0},{"month":"2021-11-01","deals":1,"median_unit_price_ping":227636.35510000002,"avg_unit_price_ping":227636.35510000002,"median_total_price":6300000.0},{"month":"2021-12-01","deals":1,"median_unit_price_ping":76928.922735,"avg_unit_price_ping":76928.922735,"median_total_price":5260000.0},{"month":"2022-01-01","deals":3,"median_unit_price_ping":192059.49693000002,"avg_unit_price_ping":193257.29302833337,"median_total_price":10700000.0},{"month":"2022-02-01","deals":1,"median_unit_price_ping":46661.155275000005,"avg_unit_price_ping":46661.155275000005,"median_total_price":5000000.0},{"month":"2022-03-01","deals":1,"median_unit_price_ping":66919.005755,"avg_unit_price_ping":66919.005755,"median_total_price":4893000.0},{"month":"2022-04-01","deals":3,"median_unit_price_ping":188112.38964,"avg_unit_price_ping":143238.56212166668,"median_total_price":10480000.0},{"month":"2022-06-01","deals":4,"median_unit_price_ping":174714.043035,"avg_unit_price_ping":162204.12614875002,"median_total_price":8360000.0},{"month":"2022-07-01","deals":27,"median_unit_price_ping":181821.48078500002,"avg_unit_price_ping":174462.06875611114,"median_total_price":8700000.0},{"month":"2022-08-01","deals":16,"median_unit_price_ping":203386.7692325,"avg_unit_price_ping":190851.645735625,"median_total_price":7540000.0},{"month":"2022-09-01","deals":22,"median_unit_price_ping":226049.5783,"avg_unit_price_ping":210894.3572304545,"median_total_price":8005000.0},{"month":"2022-10-01","deals":13,"median_unit_price_ping":219008.25625,"avg_unit_price_ping":224791.8542530769,"median_total_price":8690000.0},{"month":"2022-11-01","deals":6,"median_unit_price_ping":226907.42950750003,"avg_unit_price_ping":228640.21181166673,"median_total_price":9590000.0},{"month":"2022-12-01","deals":14,"median_unit_price_ping":193828.091905,"avg_unit_price_ping":199325.37623249998,"median_total_price":8440000.0},{"month":"2023-01-01","deals":9,"median_unit_price_ping":191163.62919500002,"avg_unit_price_ping":186695.67711277778,"median_total_price":8230000.0},{"month":"2023-02-01","deals":12,"median_unit_price_ping":209203.29794000002,"avg_unit_price_ping":217263.62821625,"median_total_price":9550000.0},{"month":"2023-03-01","deals":19,"median_unit_price_ping":192079.33164000002,"avg_unit_price_ping":193569.89269763159,"median_total_price":9480000.0},{"month":"2023-04-01","deals":32,"median_unit_price_ping":212722.3060725,"avg_unit_price_ping":219178.19426015628,"median_total_price":6415000.0},{"month":"2023-05-01","deals":11,"median_unit_price_ping":228647.92531000002,"avg_unit_price_ping":253924.25794590914,"median_total_price":7870000.0},{"month":"2023-06-01","deals":17,"median_unit_price_ping":220112.38844,"avg_unit_price_ping":225596.49129705882,"median_total_price":6830000.0},{"month":"2023-07-01","deals":3,"median_unit_price_ping":233143.79291000002,"avg_unit_price_ping":230285.39081333333,"median_total_price":6550000.0},{"month":"2023-08-01","deals":3,"median_unit_price_ping":178003.29911000002,"avg_unit_price_ping":168015.42069666667,"median_total_price":7980000.0},{"month":"2023-09-01","deals":2,"median_unit_price_ping":227085.94189750002,"avg_unit_price_ping":227085.94189750002,"median_total_price":14390000.0},{"month":"2023-10-01","deals":19,"median_unit_price_ping":209226.43843500002,"avg_unit_price_ping":210835.31179789477,"median_total_price":11200000.0},{"month":"2023-11-01","deals":21,"median_unit_price_ping":222839.66106500002,"avg_unit_price_ping":269796.29055166664,"median_total_price":10500000.0},{"month":"2023-12-01","deals":14,"median_unit_price_ping":207547.099655,"avg_unit_price_ping":206976.37948750003,"median_total_price":10080000.0},{"month":"2024-01-01","deals":18,"median_unit_price_ping":218408.25627250003,"avg_unit_price_ping":227165.8317016667,"median_total_price":10180000.0},{"month":"2024-02-01","deals":21,"median_unit_price_ping":211705.777185,"avg_unit_price_ping":185877.99381666668,"median_total_price":6500000.0},{"month":"2024-03-01","deals":21,"median_unit_price_ping":209411.56239500002,"avg_unit_price_ping":282107.34872833337,"median_total_price":10380000.0},{"month":"2024-04-01","deals":26,"median_unit_price_ping":234082.63585000002,"avg_unit_price_ping":212704.1242550001,"median_total_price":7800000.0},{"month":"2024-05-01","deals":39,"median_unit_price_ping":212469.41352,"avg_unit_price_ping":196635.2967160257,"median_total_price":5580000.0},{"month":"2024-06-01","deals":22,"median_unit_price_ping":202284.289935,"avg_unit_price_ping":186594.73379909093,"median_total_price":6625000.0},{"month":"2024-07-01","deals":20,"median_unit_price_ping":236446.27212500002,"avg_unit_price_ping":221134.37187274997,"median_total_price":13400000.0},{"month":"2024-08-01","deals":9,"median_unit_price_ping":209818.17395000003,"avg_unit_price_ping":190100.6356627778,"median_total_price":5500000.0},{"month":"2024-09-01","deals":18,"median_unit_price_ping":220067.7603425,"avg_unit_price_ping":245864.45359000005,"median_total_price":7125000.0},{"month":"2024-10-01","deals":25,"median_unit_price_ping":232238.00782000003,"avg_unit_price_ping":238763.75964139999,"median_total_price":8000000.0},{"month":"2024-11-01","deals":21,"median_unit_price_ping":238770.23898000002,"avg_unit_price_ping":266005.3422483333,"median_total_price":8500000.0},{"month":"2024-12-01","deals":11,"median_unit_price_ping":231662.80123,"avg_unit_price_ping":227985.26568045455,"median_total_price":7640000.0},{"month":"2025-01-01","deals":12,"median_unit_price_ping":207761.97568000003,"avg_unit_price_ping":243893.65476583337,"median_total_price":9414600.0},{"month":"2025-02-01","deals":6,"median_unit_price_ping":233373.54496750003,"avg_unit_price_ping":208666.65884166668,"median_total_price":7990000.0},{"month":"2025-03-01","deals":17,"median_unit_price_ping":232624.784665,"avg_unit_price_ping":256604.36568117645,"median_total_price":10500000.0},{"month":"2025-04-01","deals":6,"median_unit_price_ping":198112.389265,"avg_unit_price_ping":196383.46371,"median_total_price":6200000.0},{"month":"2025-05-01","deals":10,"median_unit_price_ping":228642.9666325,"avg_unit_price_ping":220776.52064650002,"median_total_price":11250000.0},{"month":"2025-06-01","deals":3,"median_unit_price_ping":238152.057185,"avg_unit_price_ping":283854.53481000004,"median_total_price":9000000.0},{"month":"2025-07-01","deals":11,"median_unit_price_ping":238439.66048000002,"avg_unit_price_ping":230343.79301500003,"median_total_price":12200000.0},{"month":"2025-08-01","deals":5,"median_unit_price_ping":232780.15656,"avg_unit_price_ping":211097.512745,"median_total_price":7600000.0},{"month":"2025-09-01","deals":19,"median_unit_price_ping":233107.429275,"avg_unit_price_ping":184388.33584315787,"median_total_price":6600000.0},{"month":"2025-10-01","deals":7,"median_unit_price_ping":132115.697525,"avg_unit_price_ping":173629.745555,"median_total_price":7300000.0},{"month":"2025-11-01","deals":6,"median_unit_price_ping":225284.28907250002,"avg_unit_price_ping":230169.68833833336,"median_total_price":8940000.0},{"month":"2025-12-01","deals":12,"median_unit_price_ping":195310.7364775,"avg_unit_price_ping":190285.11683125,"median_total_price":9990000.0},{"month":"2026-01-01","deals":6,"median_unit_price_ping":304099.16215,"avg_unit_price_ping":310840.2087291667,"median_total_price":7750000.0},{"month":"2026-02-01","deals":3,"median_unit_price_ping":241186.76781500003,"avg_unit_price_ping":231647.37423333336,"median_total_price":9600000.0}]