[{"month":"2023-06-01","deals":2,"median_unit_price_ping":205323.95924250002,"avg_unit_price_ping":205323.95924250002,"median_total_price":30500000.0},{"month":"2023-10-01","deals":1,"median_unit_price_ping":160142.142755,"avg_unit_price_ping":160142.142755,"median_total_price":8341447.0},{"month":"2023-11-01","deals":5,"median_unit_price_ping":153061.151285,"avg_unit_price_ping":205391.727835,"median_total_price":15000000.0},{"month":"2023-12-01","deals":1,"median_unit_price_ping":563229.7309450001,"avg_unit_price_ping":563229.7309450001,"median_total_price":15000000.0},{"month":"2024-01-01","deals":1,"median_unit_price_ping":256783.46144500002,"avg_unit_price_ping":256783.46144500002,"median_total_price":4280000.0},{"month":"2024-03-01","deals":2,"median_unit_price_ping":417892.5463125,"avg_unit_price_ping":417892.5463125,"median_total_price":15400000.0},{"month":"2024-06-01","deals":1,"median_unit_price_ping":389322.29945000005,"avg_unit_price_ping":389322.29945000005,"median_total_price":10750000.0},{"month":"2024-08-01","deals":2,"median_unit_price_ping":392438.0018125,"avg_unit_price_ping":392438.0018125,"median_total_price":5600000.0},{"month":"2024-09-01","deals":1,"median_unit_price_ping":85414.87283000001,"avg_unit_price_ping":85414.87283000001,"median_total_price":4600000.0},{"month":"2024-10-01","deals":1,"median_unit_price_ping":1129976.81713,"avg_unit_price_ping":1129976.81713,"median_total_price":18800000.0},{"month":"2024-11-01","deals":2,"median_unit_price_ping":68884.2949375,"avg_unit_price_ping":68884.2949375,"median_total_price":2200000.0},{"month":"2024-12-01","deals":1,"median_unit_price_ping":93434.70724,"avg_unit_price_ping":93434.70724,"median_total_price":8600000.0},{"month":"2025-01-01","deals":1,"median_unit_price_ping":151071.068715,"avg_unit_price_ping":151071.068715,"median_total_price":4000000.0},{"month":"2025-02-01","deals":1,"median_unit_price_ping":53315.70048,"avg_unit_price_ping":53315.70048,"median_total_price":4000000.0},{"month":"2025-04-01","deals":2,"median_unit_price_ping":343214.8631625,"avg_unit_price_ping":343214.8631625,"median_total_price":14250000.0},{"month":"2025-05-01","deals":1,"median_unit_price_ping":148413.21757500002,"avg_unit_price_ping":148413.21757500002,"median_total_price":8100000.0},{"month":"2025-08-01","deals":1,"median_unit_price_ping":170909.0845,"avg_unit_price_ping":170909.0845,"median_total_price":16000000.0},{"month":"2025-10-01","deals":1,"median_unit_price_ping":755117.327055,"avg_unit_price_ping":755117.327055,"median_total_price":29800000.0},{"month":"2025-11-01","deals":1,"median_unit_price_ping":118069.41706,"avg_unit_price_ping":118069.41706,"median_total_price":11700000.0},{"month":"2025-12-01","deals":1,"median_unit_price_ping":163854.53931000002,"avg_unit_price_ping":163854.53931000002,"median_total_price":10000000.0},{"month":"2026-01-01","deals":1,"median_unit_price_ping":253973.54419500002,"avg_unit_price_ping":253973.54419500002,"median_total_price":7400000.0}]