[{"month":"2021-09-01","deals":4,"median_unit_price_ping":181803.2989675,"avg_unit_price_ping":179812.38995125,"median_total_price":9510000.0},{"month":"2021-10-01","deals":7,"median_unit_price_ping":183599.99311500002,"avg_unit_price_ping":186320.65417000002,"median_total_price":9520000.0},{"month":"2021-11-01","deals":3,"median_unit_price_ping":168132.2251,"avg_unit_price_ping":158764.73233833336,"median_total_price":10500000.0},{"month":"2021-12-01","deals":7,"median_unit_price_ping":183216.522055,"avg_unit_price_ping":187567.40737,"median_total_price":10600000.0},{"month":"2022-01-01","deals":1,"median_unit_price_ping":183216.522055,"avg_unit_price_ping":183216.522055,"median_total_price":9500000.0},{"month":"2022-02-01","deals":2,"median_unit_price_ping":189033.0507625,"avg_unit_price_ping":189033.0507625,"median_total_price":10300000.0},{"month":"2022-03-01","deals":2,"median_unit_price_ping":228910.7352175,"avg_unit_price_ping":228910.7352175,"median_total_price":12350000.0},{"month":"2022-04-01","deals":6,"median_unit_price_ping":188221.480545,"avg_unit_price_ping":190246.82482166667,"median_total_price":10090000.0},{"month":"2022-05-01","deals":2,"median_unit_price_ping":190395.0341825,"avg_unit_price_ping":190395.0341825,"median_total_price":9850000.0},{"month":"2022-06-01","deals":2,"median_unit_price_ping":239204.9497075,"avg_unit_price_ping":239204.9497075,"median_total_price":10935000.0},{"month":"2022-07-01","deals":3,"median_unit_price_ping":230023.13187,"avg_unit_price_ping":237477.67704500002,"median_total_price":12760000.0},{"month":"2022-09-01","deals":2,"median_unit_price_ping":249395.03197,"avg_unit_price_ping":249395.03197,"median_total_price":9790000.0},{"month":"2022-10-01","deals":3,"median_unit_price_ping":259170.23821500002,"avg_unit_price_ping":239433.5998366667,"median_total_price":9180000.0},{"month":"2022-11-01","deals":2,"median_unit_price_ping":244938.83379,"avg_unit_price_ping":244938.83379,"median_total_price":10925000.0},{"month":"2022-12-01","deals":37,"median_unit_price_ping":217014.867895,"avg_unit_price_ping":227932.53556689192,"median_total_price":8480000.0},{"month":"2023-01-01","deals":4,"median_unit_price_ping":233335.52844000002,"avg_unit_price_ping":238625.61088625,"median_total_price":8740000.0},{"month":"2023-02-01","deals":15,"median_unit_price_ping":254323.95740500002,"avg_unit_price_ping":240714.92210266663,"median_total_price":8000000.0},{"month":"2023-03-01","deals":11,"median_unit_price_ping":228786.76828000002,"avg_unit_price_ping":233954.3112868182,"median_total_price":8580000.0},{"month":"2023-04-01","deals":6,"median_unit_price_ping":240399.990985,"avg_unit_price_ping":242499.71542416667,"median_total_price":8640000.0},{"month":"2023-05-01","deals":7,"median_unit_price_ping":241447.92483,"avg_unit_price_ping":241161.266045,"median_total_price":8760000.0},{"month":"2023-06-01","deals":7,"median_unit_price_ping":245537.18087500002,"avg_unit_price_ping":245960.32135500005,"median_total_price":8900000.0},{"month":"2023-07-01","deals":5,"median_unit_price_ping":231725.611145,"avg_unit_price_ping":242208.25538,"median_total_price":10080000.0},{"month":"2023-08-01","deals":11,"median_unit_price_ping":254244.618565,"avg_unit_price_ping":245590.67448681817,"median_total_price":7880000.0},{"month":"2023-09-01","deals":8,"median_unit_price_ping":287095.8570025,"avg_unit_price_ping":287547.92310125,"median_total_price":8560000.0},{"month":"2023-10-01","deals":11,"median_unit_price_ping":244251.23051000002,"avg_unit_price_ping":247945.29498454547,"median_total_price":12500000.0},{"month":"2023-11-01","deals":29,"median_unit_price_ping":208919.00043000001,"avg_unit_price_ping":218910.3366184483,"median_total_price":9200000.0},{"month":"2023-12-01","deals":11,"median_unit_price_ping":210323.959055,"avg_unit_price_ping":229767.08379545456,"median_total_price":12220000.0},{"month":"2024-01-01","deals":13,"median_unit_price_ping":246327.26349,"avg_unit_price_ping":245306.79308961547,"median_total_price":13300000.0},{"month":"2024-02-01","deals":21,"median_unit_price_ping":253229.74257,"avg_unit_price_ping":244842.021515,"median_total_price":11300000.0},{"month":"2024-03-01","deals":21,"median_unit_price_ping":226664.45431,"avg_unit_price_ping":227295.85924500006,"median_total_price":10250000.0},{"month":"2024-04-01","deals":19,"median_unit_price_ping":236016.520075,"avg_unit_price_ping":226578.3299113158,"median_total_price":9400000.0},{"month":"2024-05-01","deals":20,"median_unit_price_ping":242401.6438025,"avg_unit_price_ping":233012.22266699997,"median_total_price":12050000.0},{"month":"2024-06-01","deals":17,"median_unit_price_ping":244271.06522000002,"avg_unit_price_ping":236989.58761264704,"median_total_price":11120000.0},{"month":"2024-07-01","deals":24,"median_unit_price_ping":225031.39652,"avg_unit_price_ping":226833.6003091667,"median_total_price":9650000.0},{"month":"2024-08-01","deals":12,"median_unit_price_ping":243890.899945,"avg_unit_price_ping":245308.25526375,"median_total_price":12100000.0},{"month":"2024-09-01","deals":15,"median_unit_price_ping":215963.628265,"avg_unit_price_ping":231503.462393,"median_total_price":9380000.0},{"month":"2024-10-01","deals":11,"median_unit_price_ping":200902.471805,"avg_unit_price_ping":190931.02214136365,"median_total_price":7860000.0},{"month":"2024-11-01","deals":16,"median_unit_price_ping":245702.47012500002,"avg_unit_price_ping":252472.30458187498,"median_total_price":10750000.0},{"month":"2024-12-01","deals":11,"median_unit_price_ping":224776.851075,"avg_unit_price_ping":231373.99583136366,"median_total_price":10980000.0},{"month":"2025-01-01","deals":13,"median_unit_price_ping":250595.03192500002,"avg_unit_price_ping":263358.41351884615,"median_total_price":10580000.0},{"month":"2025-02-01","deals":12,"median_unit_price_ping":229928.9169975,"avg_unit_price_ping":256283.18598166667,"median_total_price":7700000.0},{"month":"2025-03-01","deals":13,"median_unit_price_ping":242958.66857500002,"avg_unit_price_ping":233612.7057976923,"median_total_price":9800000.0},{"month":"2025-04-01","deals":13,"median_unit_price_ping":221550.40491500002,"avg_unit_price_ping":205897.51294000002,"median_total_price":9300000.0},{"month":"2025-05-01","deals":11,"median_unit_price_ping":226452.88407,"avg_unit_price_ping":235539.88598318183,"median_total_price":11000000.0},{"month":"2025-06-01","deals":6,"median_unit_price_ping":204545.44687500002,"avg_unit_price_ping":271531.11929416674,"median_total_price":11680000.0},{"month":"2025-07-01","deals":6,"median_unit_price_ping":163429.74593750003,"avg_unit_price_ping":216137.73294166665,"median_total_price":7610000.0},{"month":"2025-08-01","deals":10,"median_unit_price_ping":178267.76191,"avg_unit_price_ping":220615.85949550002,"median_total_price":8925000.0},{"month":"2025-09-01","deals":14,"median_unit_price_ping":221436.3553325,"avg_unit_price_ping":225776.61491,"median_total_price":9780000.0},{"month":"2025-10-01","deals":12,"median_unit_price_ping":267666.10566500004,"avg_unit_price_ping":251268.31013666667,"median_total_price":9070000.0},{"month":"2025-11-01","deals":11,"median_unit_price_ping":245907.428795,"avg_unit_price_ping":257243.5666118182,"median_total_price":11800000.0},{"month":"2025-12-01","deals":7,"median_unit_price_ping":252985.11448000002,"avg_unit_price_ping":257703.88644,"median_total_price":8450000.0},{"month":"2026-01-01","deals":4,"median_unit_price_ping":264256.18843750004,"avg_unit_price_ping":240365.2802425,"median_total_price":6925000.0},{"month":"2026-02-01","deals":1,"median_unit_price_ping":196905.77774000002,"avg_unit_price_ping":196905.77774000002,"median_total_price":5580000.0}]