[{"month":"2023-05-01","deals":1,"median_unit_price_ping":231097.511995,"avg_unit_price_ping":231097.511995,"median_total_price":139824200.0},{"month":"2023-10-01","deals":2,"median_unit_price_ping":118123.9625125,"avg_unit_price_ping":118123.9625125,"median_total_price":10500000.0},{"month":"2023-12-01","deals":2,"median_unit_price_ping":191942.1415625,"avg_unit_price_ping":191942.1415625,"median_total_price":11000000.0},{"month":"2024-01-01","deals":4,"median_unit_price_ping":204894.2071925,"avg_unit_price_ping":204588.42208000002,"median_total_price":9775000.0},{"month":"2024-02-01","deals":1,"median_unit_price_ping":108472.723205,"avg_unit_price_ping":108472.723205,"median_total_price":78500000.0},{"month":"2024-04-01","deals":1,"median_unit_price_ping":208796.686385,"avg_unit_price_ping":208796.686385,"median_total_price":13200000.0},{"month":"2024-05-01","deals":8,"median_unit_price_ping":207565.2814725,"avg_unit_price_ping":205769.41377125002,"median_total_price":9550000.0},{"month":"2024-06-01","deals":5,"median_unit_price_ping":134998.342045,"avg_unit_price_ping":143537.1847,"median_total_price":9650000.0},{"month":"2024-07-01","deals":2,"median_unit_price_ping":224003.297385,"avg_unit_price_ping":224003.297385,"median_total_price":10725000.0},{"month":"2024-09-01","deals":3,"median_unit_price_ping":7170.247665000001,"avg_unit_price_ping":7278.236641666667,"median_total_price":618300.0},{"month":"2024-10-01","deals":1,"median_unit_price_ping":147242.96968500002,"avg_unit_price_ping":147242.96968500002,"median_total_price":3500000.0},{"month":"2024-12-01","deals":1,"median_unit_price_ping":50241.32043,"avg_unit_price_ping":50241.32043,"median_total_price":2200000.0},{"month":"2025-02-01","deals":2,"median_unit_price_ping":163074.37405,"avg_unit_price_ping":163074.37405,"median_total_price":6575000.0},{"month":"2025-03-01","deals":1,"median_unit_price_ping":29910.742680000003,"avg_unit_price_ping":29910.742680000003,"median_total_price":26000000.0},{"month":"2025-05-01","deals":1,"median_unit_price_ping":130492.55709,"avg_unit_price_ping":130492.55709,"median_total_price":3900000.0},{"month":"2025-06-01","deals":1,"median_unit_price_ping":180895.860985,"avg_unit_price_ping":180895.860985,"median_total_price":4300000.0},{"month":"2025-07-01","deals":2,"median_unit_price_ping":1093277.6449525,"avg_unit_price_ping":1093277.6449525,"median_total_price":181500000.0},{"month":"2025-10-01","deals":1,"median_unit_price_ping":50760.328675000004,"avg_unit_price_ping":50760.328675000004,"median_total_price":1900000.0},{"month":"2025-11-01","deals":5,"median_unit_price_ping":210664.45491,"avg_unit_price_ping":176918.34047300002,"median_total_price":12800000.0},{"month":"2025-12-01","deals":3,"median_unit_price_ping":223775.19822000002,"avg_unit_price_ping":184620.37875166666,"median_total_price":12000000.0},{"month":"2026-01-01","deals":1,"median_unit_price_ping":96175.203005,"avg_unit_price_ping":96175.203005,"median_total_price":3600000.0}]