[{"month":"2023-02-01","deals":2,"median_unit_price_ping":174195.03479,"avg_unit_price_ping":174195.03479,"median_total_price":9500000.0},{"month":"2023-03-01","deals":3,"median_unit_price_ping":187236.356615,"avg_unit_price_ping":184401.09501333334,"median_total_price":9900000.0},{"month":"2023-05-01","deals":1,"median_unit_price_ping":172105.77867,"avg_unit_price_ping":172105.77867,"median_total_price":9100000.0},{"month":"2023-10-01","deals":1,"median_unit_price_ping":204257.84358000002,"avg_unit_price_ping":204257.84358000002,"median_total_price":10800000.0},{"month":"2023-11-01","deals":1,"median_unit_price_ping":188786.76978,"avg_unit_price_ping":188786.76978,"median_total_price":4250000.0},{"month":"2023-12-01","deals":4,"median_unit_price_ping":36669.4201125,"avg_unit_price_ping":41435.53563625,"median_total_price":1350000.0},{"month":"2024-01-01","deals":4,"median_unit_price_ping":171995.03487250002,"avg_unit_price_ping":172162.80346125,"median_total_price":6300000.0},{"month":"2024-02-01","deals":4,"median_unit_price_ping":106406.60758000001,"avg_unit_price_ping":108857.02071125,"median_total_price":4350000.0},{"month":"2024-03-01","deals":7,"median_unit_price_ping":144333.878885,"avg_unit_price_ping":128990.78619000001,"median_total_price":5700000.0},{"month":"2024-04-01","deals":2,"median_unit_price_ping":170540.4894725,"avg_unit_price_ping":170540.4894725,"median_total_price":14400000.0},{"month":"2024-05-01","deals":1,"median_unit_price_ping":70961.98081000001,"avg_unit_price_ping":70961.98081000001,"median_total_price":2800000.0},{"month":"2024-06-01","deals":1,"median_unit_price_ping":131398.34218,"avg_unit_price_ping":131398.34218,"median_total_price":9700000.0},{"month":"2024-07-01","deals":4,"median_unit_price_ping":104433.053935,"avg_unit_price_ping":114652.8882625,"median_total_price":6125000.0},{"month":"2024-08-01","deals":2,"median_unit_price_ping":64543.7992325,"avg_unit_price_ping":64543.7992325,"median_total_price":1535000.0},{"month":"2024-10-01","deals":2,"median_unit_price_ping":180036.35688500002,"avg_unit_price_ping":180036.35688500002,"median_total_price":6930000.0},{"month":"2024-11-01","deals":2,"median_unit_price_ping":107100.82243,"avg_unit_price_ping":107100.82243,"median_total_price":7450000.0},{"month":"2024-12-01","deals":1,"median_unit_price_ping":73061.15428500001,"avg_unit_price_ping":73061.15428500001,"median_total_price":4000000.0},{"month":"2025-02-01","deals":3,"median_unit_price_ping":59676.03082,"avg_unit_price_ping":61032.50459833333,"median_total_price":1900000.0},{"month":"2025-03-01","deals":2,"median_unit_price_ping":149497.51505500003,"avg_unit_price_ping":149497.51505500003,"median_total_price":7740000.0},{"month":"2025-04-01","deals":2,"median_unit_price_ping":142504.1268875,"avg_unit_price_ping":142504.1268875,"median_total_price":8400000.0},{"month":"2025-06-01","deals":2,"median_unit_price_ping":137122.3089075,"avg_unit_price_ping":137122.3089075,"median_total_price":10750000.0},{"month":"2025-07-01","deals":2,"median_unit_price_ping":134399.99496,"avg_unit_price_ping":134399.99496,"median_total_price":6800000.0},{"month":"2025-09-01","deals":2,"median_unit_price_ping":111451.23549,"avg_unit_price_ping":111451.23549,"median_total_price":6275000.0},{"month":"2025-10-01","deals":1,"median_unit_price_ping":194866.10839500002,"avg_unit_price_ping":194866.10839500002,"median_total_price":21330000.0},{"month":"2025-11-01","deals":1,"median_unit_price_ping":104419.830795,"avg_unit_price_ping":104419.830795,"median_total_price":2575000.0},{"month":"2025-12-01","deals":3,"median_unit_price_ping":116733.87992,"avg_unit_price_ping":105781.81421500002,"median_total_price":5450000.0},{"month":"2026-01-01","deals":6,"median_unit_price_ping":154988.42394,"avg_unit_price_ping":160116.79840333332,"median_total_price":4530000.0},{"month":"2026-03-01","deals":1,"median_unit_price_ping":145543.796195,"avg_unit_price_ping":145543.796195,"median_total_price":8900000.0}]