[{"serial_no":"RPUNMLMKKHLGFBE97DA","district":"苓雅區","address":"高雄市苓雅區三多四路６３號地下層之１１９","road":"苓雅區三多四路","building_type":"住宅大樓(11層含以上有電梯)","total_floors":19.0,"transfer_floor_num":null,"age_years":35.7,"rooms":0.0,"halls":0.0,"baths":0.0,"building_area_sqm":31.060000000000002,"total_price":85000,"unit_price_per_ping":9047.933545,"deal_date":"2026-02-07","region_p25":202509.90976125002,"price_ratio":0.04467896684990429},{"serial_no":"RPQNMLMLJHLGFLE58DA","district":"大寮區","address":"高雄市大寮區鳳林三路４３１號","road":"大寮區鳳林三路","building_type":"透天厝","total_floors":1.0,"transfer_floor_num":null,"age_years":7.0,"rooms":0.0,"halls":0.0,"baths":0.0,"building_area_sqm":305.47,"total_price":2000000,"unit_price_per_ping":21642.974395,"deal_date":"2026-01-13","region_p25":157065.28336625,"price_ratio":0.13779604207336005},{"serial_no":"RPXNMLTLKIKGFLE47DA","district":"大寮區","address":"高雄市大寮區鳳林三路２４７巷１２號","road":"大寮區鳳林三路","building_type":"透天厝","total_floors":2.0,"transfer_floor_num":null,"age_years":48.6,"rooms":2.0,"halls":2.0,"baths":2.0,"building_area_sqm":46.0,"total_price":380000,"unit_price_per_ping":27309.089885,"deal_date":"2025-12-18","region_p25":157065.28336625,"price_ratio":0.17387094907102907},{"serial_no":"RPRNMLMKKIKGFGE18DA","district":"鳳山區","address":"高雄市鳳山區信義街２９之３２號","road":"鳳山區信義街","building_type":"華廈(10層含以下有電梯)","total_floors":6.0,"transfer_floor_num":6.0,"age_years":49.0,"rooms":2.0,"halls":1.0,"baths":1.0,"building_area_sqm":64.15,"total_price":735000,"unit_price_per_ping":37877.68453,"deal_date":"2025-12-11","region_p25":190051.23254250002,"price_ratio":0.19930249345544043},{"serial_no":"RPSNMLSLJHLGFJE56DA","district":"路竹區","address":"高雄市路竹區太平路３２７巷５１號","road":"路竹區太平路","building_type":"透天厝","total_floors":2.0,"transfer_floor_num":null,"age_years":46.1,"rooms":3.0,"halls":2.0,"baths":1.0,"building_area_sqm":90.96,"total_price":1000000,"unit_price_per_ping":36343.80029,"deal_date":"2026-01-08","region_p25":179847.10069375002,"price_ratio":0.20208165797394478},{"serial_no":"RPPNMLLJKIKGFEE57DA","district":"楠梓區","address":"高雄市楠梓區內環南路１１８號","road":"楠梓區內環南路","building_type":"透天厝","total_floors":3.0,"transfer_floor_num":null,"age_years":54.5,"rooms":0.0,"halls":0.0,"baths":0.0,"building_area_sqm":13516.55,"total_price":230000000,"unit_price_per_ping":56251.23756,"deal_date":"2025-11-25","region_p25":269958.6675625,"price_ratio":0.2083698147864687},{"serial_no":"RPUNMLSJKIKGFCE58DA","district":"前鎮區","address":"高雄市前鎮區新生路２９７巷２０號","road":"前鎮區新生路","building_type":"透天厝","total_floors":3.0,"transfer_floor_num":null,"age_years":50.3,"rooms":0.0,"halls":0.0,"baths":0.0,"building_area_sqm":271.11,"total_price":3950000,"unit_price_per_ping":48165.28745,"deal_date":"2025-12-03","region_p25":220160.32232250003,"price_ratio":0.2187736961042666},{"serial_no":"RPSOMLNLKHLGFBE08DA","district":"新興區","address":"高雄市新興區仁愛一街２９３號地下室","road":"新興區仁愛一街","building_type":"華廈(10層含以下有電梯)","total_floors":8.0,"transfer_floor_num":null,"age_years":45.4,"rooms":0.0,"halls":1.0,"baths":2.0,"building_area_sqm":540.8,"total_price":9200000,"unit_price_per_ping":56238.01442000001,"deal_date":"2025-12-31","region_p25":190290.90195500004,"price_ratio":0.29553706373886},{"serial_no":"RPPNMLNLJIKGFJE38DA","district":"茄萣區","address":"高雄市茄萣區金鑾路１６５巷１３弄１０號","road":"茄萣區金鑾路","building_type":"透天厝","total_floors":2.0,"transfer_floor_num":null,"age_years":51.4,"rooms":4.0,"halls":2.0,"baths":2.0,"building_area_sqm":88.32,"total_price":1600000,"unit_price_per_ping":59887.60106,"deal_date":"2025-11-11","region_p25":186544.62110375002,"price_ratio":0.32103633278545446},{"serial_no":"RPRPMLNLKIKGFEE38DA","district":"左營區","address":"高雄市左營區自由三路４１０號三樓","road":"左營區自由三路","building_type":"華廈(10層含以下有電梯)","total_floors":7.0,"transfer_floor_num":3.0,"age_years":30.2,"rooms":0.0,"halls":0.0,"baths":0.0,"building_area_sqm":913.4200000000001,"total_price":20400000,"unit_price_per_ping":73831.40219000001,"deal_date":"2025-12-01","region_p25":222850.40486625,"price_ratio":0.33130477027543215},{"serial_no":"RPSPMLNLKIKGFEE48DA","district":"左營區","address":"高雄市左營區自由三路４１０號四樓","road":"左營區自由三路","building_type":"華廈(10層含以下有電梯)","total_floors":7.0,"transfer_floor_num":4.0,"age_years":30.2,"rooms":0.0,"halls":0.0,"baths":0.0,"building_area_sqm":608.95,"total_price":13600000,"unit_price_per_ping":73831.40219000001,"deal_date":"2025-12-01","region_p25":222850.40486625,"price_ratio":0.33130477027543215},{"serial_no":"RPRNMLMLKIKGFIE48DA","district":"鳥松區","address":"高雄市鳥松區松埔北巷１１之８號","road":null,"building_type":"華廈(10層含以下有電梯)","total_floors":7.0,"transfer_floor_num":1.0,"age_years":35.2,"rooms":1.0,"halls":1.0,"baths":1.0,"building_area_sqm":61.55,"total_price":1100000,"unit_price_per_ping":59080.98952,"deal_date":"2025-11-14","region_p25":168798.3407775,"price_ratio":0.35000930250776024},{"serial_no":"RPXNMLNLJHLGFBE38DA","district":"苓雅區","address":"高雄市苓雅區仁愛三街２５１巷６號","road":"苓雅區仁愛三街","building_type":"透天厝","total_floors":2.0,"transfer_floor_num":null,"age_years":57.9,"rooms":5.0,"halls":2.0,"baths":3.0,"building_area_sqm":79.17,"total_price":2280000,"unit_price_per_ping":95203.302215,"deal_date":"2026-01-12","region_p25":270218.171685,"price_ratio":0.3523201331033386},{"serial_no":"RPPNMLLLJHLGFEE77EA","district":"楠梓區","address":"高雄市楠梓區右昌街１００巷１２號","road":"楠梓區右昌街","building_type":"透天厝","total_floors":3.0,"transfer_floor_num":null,"age_years":11.1,"rooms":6.0,"halls":3.0,"baths":4.0,"building_area_sqm":198.56,"total_price":6000000,"unit_price_per_ping":99894.21113000001,"deal_date":"2026-01-02","region_p25":269958.6675625,"price_ratio":0.37003520587785094},{"serial_no":"RPTNMLKKKHLGFGE18DA","district":"鳳山區","address":"高雄市鳳山區瑞大街３４號","road":"鳳山區瑞大街","building_type":"透天厝","total_floors":2.0,"transfer_floor_num":null,"age_years":39.3,"rooms":4.0,"halls":2.0,"baths":3.0,"building_area_sqm":113.09,"total_price":3000000,"unit_price_per_ping":87695.86448,"deal_date":"2026-01-23","region_p25":235879.32999750003,"price_ratio":0.37178274366359043},{"serial_no":"RPPNMLNJLHLGFJE38DA","district":"茄萣區","address":"高雄市茄萣區尚禮街５４號","road":"茄萣區尚禮街","building_type":"透天厝","total_floors":4.0,"transfer_floor_num":null,"age_years":33.7,"rooms":4.0,"halls":3.0,"baths":3.0,"building_area_sqm":181.87,"total_price":3850000,"unit_price_per_ping":69980.16266500001,"deal_date":"2025-12-31","region_p25":186544.62110375002,"price_ratio":0.37513900026138697},{"serial_no":"RPWNMLKKKIKGFDE18DA","district":"三民區","address":"高雄市三民區建德路２１０巷６弄５號三樓之３","road":"三民區建德路","building_type":"公寓(5樓含以下無電梯)","total_floors":5.0,"transfer_floor_num":3.0,"age_years":46.0,"rooms":3.0,"halls":1.0,"baths":2.0,"building_area_sqm":57.72,"total_price":980000,"unit_price_per_ping":56128.923515,"deal_date":"2025-11-18","region_p25":148305.7795625,"price_ratio":0.3784675397046531},{"serial_no":"RPPNMLOJLHLGFDE97EA","district":"三民區","address":"高雄市三民區建國三路８３號十一樓之７","road":"三民區建國三路","building_type":"住宅大樓(11層含以上有電梯)","total_floors":12.0,"transfer_floor_num":11.0,"age_years":35.2,"rooms":1.0,"halls":0.0,"baths":1.0,"building_area_sqm":31.78,"total_price":830000,"unit_price_per_ping":86337.186845,"deal_date":"2026-02-23","region_p25":227968.5864925,"price_ratio":0.3787240521747957},{"serial_no":"RPTPMLRKKIKGFIE66DA","district":"仁武區","address":"高雄市仁武區大福街２５８號五樓之２","road":"仁武區大福街","building_type":"公寓(5樓含以下無電梯)","total_floors":5.0,"transfer_floor_num":5.0,"age_years":44.6,"rooms":3.0,"halls":2.0,"baths":2.0,"building_area_sqm":100.92,"total_price":1300000,"unit_price_per_ping":42581.816585,"deal_date":"2025-12-07","region_p25":110433.05371000001,"price_ratio":0.38558941507513617},{"serial_no":"RPUNMLMKKIKGFJE78DA","district":"阿蓮區","address":"高雄市阿蓮區民權路５８巷１４號","road":"阿蓮區民權路","building_type":"透天厝","total_floors":2.0,"transfer_floor_num":null,"age_years":null,"rooms":2.0,"halls":1.0,"baths":2.0,"building_area_sqm":88.54,"total_price":1400000,"unit_price_per_ping":52271.072420000004,"deal_date":"2025-12-10","region_p25":130523.96204749998,"price_ratio":0.4004710828573962},{"serial_no":"RPWNMLPLKHLGFCE68DA","district":"前鎮區","address":"高雄市前鎮區佛中路６４號六樓","road":"前鎮區佛中路","building_type":"住宅大樓(11層含以上有電梯)","total_floors":14.0,"transfer_floor_num":6.0,"age_years":34.8,"rooms":0.0,"halls":0.0,"baths":0.0,"building_area_sqm":178.18,"total_price":5150000,"unit_price_per_ping":95547.10385500001,"deal_date":"2025-12-26","region_p25":235854.53661,"price_ratio":0.40511030751548793},{"serial_no":"RPVNMLNLKHLGFIE98DA","district":"鳥松區","address":"高雄市鳥松區松埔北巷１１之１１５號","road":null,"building_type":"華廈(10層含以下有電梯)","total_floors":7.0,"transfer_floor_num":4.0,"age_years":35.4,"rooms":2.0,"halls":0.0,"baths":2.0,"building_area_sqm":110.80000000000001,"total_price":2400000,"unit_price_per_ping":71606.60888500001,"deal_date":"2026-02-07","region_p25":168798.3407775,"price_ratio":0.4242139380942589},{"serial_no":"RPPNMLTLJHLGFEE48DA","district":"左營區","address":"高雄市左營區海平路１６４巷５號五樓","road":"左營區海平路","building_type":"公寓(5樓含以下無電梯)","total_floors":5.0,"transfer_floor_num":5.0,"age_years":39.7,"rooms":3.0,"halls":2.0,"baths":2.0,"building_area_sqm":100.38,"total_price":1680000,"unit_price_per_ping":55325.61776,"deal_date":"2026-01-21","region_p25":129170.24309,"price_ratio":0.4283155039156472},{"serial_no":"RPPNMLPJKIKGFCE77DA","district":"前鎮區","address":"高雄市前鎮區復興四路１２號四樓之１之２","road":"前鎮區復興四路","building_type":"住宅大樓(11層含以上有電梯)","total_floors":12.0,"transfer_floor_num":4.0,"age_years":17.8,"rooms":0.0,"halls":0.0,"baths":0.0,"building_area_sqm":333.2,"total_price":10500000,"unit_price_per_ping":102591.73169,"deal_date":"2025-11-05","region_p25":235854.53661,"price_ratio":0.4349788355338772},{"serial_no":"RPTOMLSJJHLGFGE88DA","district":"鳳山區","address":"高雄市鳳山區西湖街５８號三樓","road":"鳳山區西湖街","building_type":"住宅大樓(11層含以上有電梯)","total_floors":15.0,"transfer_floor_num":3.0,"age_years":31.1,"rooms":2.0,"halls":1.0,"baths":1.0,"building_area_sqm":69.5,"total_price":2050000,"unit_price_per_ping":97507.43436,"deal_date":"2025-12-15","region_p25":217654.5372925,"price_ratio":0.447991737608311},{"serial_no":"RPSOMLMLKIKGFGE48DA","district":"鳳山區","address":"高雄市鳳山區福安一街３９之４號","road":"鳳山區福安一街","building_type":"公寓(5樓含以下無電梯)","total_floors":5.0,"transfer_floor_num":5.0,"age_years":45.6,"rooms":2.0,"halls":1.0,"baths":1.0,"building_area_sqm":63.72,"total_price":1200000,"unit_price_per_ping":62254.54312,"deal_date":"2025-12-22","region_p25":133480.98673,"price_ratio":0.46639259002427064},{"serial_no":"RPRNMLNJLHLGFIE48DA","district":"仁武區","address":"高雄市仁武區仁林路２６７巷９弄６號","road":"仁武區仁林路","building_type":"透天厝","total_floors":4.0,"transfer_floor_num":null,"age_years":32.2,"rooms":4.0,"halls":2.0,"baths":2.0,"building_area_sqm":183.97,"total_price":6200000,"unit_price_per_ping":111408.26028500001,"deal_date":"2026-01-31","region_p25":238818.1728625,"price_ratio":0.4664982524137454},{"serial_no":"RPROMLMJJHLGFCE67DA","district":"小港區","address":"高雄市小港區康莊路８８巷１號十樓","road":"小港區康莊路","building_type":"住宅大樓(11層含以上有電梯)","total_floors":15.0,"transfer_floor_num":10.0,"age_years":28.0,"rooms":3.0,"halls":2.0,"baths":2.0,"building_area_sqm":143.13,"total_price":4300000,"unit_price_per_ping":99315.698755,"deal_date":"2025-11-17","region_p25":211280.15736625,"price_ratio":0.4700663800758071},{"serial_no":"RPQNMLTLJHLGFJE09DA","district":"阿蓮區","address":"高雄市阿蓮區成功街３巷１０號三樓之一","road":"阿蓮區成功街","building_type":"華廈(10層含以下有電梯)","total_floors":7.0,"transfer_floor_num":3.0,"age_years":31.2,"rooms":4.0,"halls":2.0,"baths":2.0,"building_area_sqm":149.57,"total_price":5120000,"unit_price_per_ping":113160.326335,"deal_date":"2025-12-15","region_p25":240033.04885000002,"price_ratio":0.4714364412615342},{"serial_no":"RPTOMLTLKIKGFLE17DA","district":"大寮區","address":"高雄市大寮區鳳林三路４７８巷４之４號","road":"大寮區鳳林三路","building_type":"透天厝","total_floors":4.0,"transfer_floor_num":null,"age_years":35.6,"rooms":6.0,"halls":2.0,"baths":3.0,"building_area_sqm":163.11,"total_price":3660000,"unit_price_per_ping":74178.509615,"deal_date":"2025-12-26","region_p25":157065.28336625,"price_ratio":0.4722782019373951},{"serial_no":"RPQOMLTKJIKGFEE58DA","district":"左營區","address":"高雄市左營區果峰街３巷１０號九樓","road":"左營區果峰街","building_type":"住宅大樓(11層含以上有電梯)","total_floors":18.0,"transfer_floor_num":9.0,"age_years":40.0,"rooms":3.0,"halls":2.0,"baths":2.0,"building_area_sqm":111.98,"total_price":3950000,"unit_price_per_ping":116608.26009000001,"deal_date":"2025-11-14","region_p25":245678.50318375003,"price_ratio":0.4746376202185884},{"serial_no":"RPRNMLTJMHLGFDE68DA","district":"三民區","address":"高雄市三民區陽明路２２９號三樓","road":"三民區陽明路","building_type":"住宅大樓(11層含以上有電梯)","total_floors":14.0,"transfer_floor_num":null,"age_years":32.4,"rooms":3.0,"halls":2.0,"baths":2.0,"building_area_sqm":106.78999999999999,"total_price":3500000,"unit_price_per_ping":108347.103375,"deal_date":"2026-03-04","region_p25":227968.5864925,"price_ratio":0.47527207604353217},{"serial_no":"RPQNMLLKKHLGFBE47DA","district":"苓雅區","address":"高雄市苓雅區中正一路１０５巷６號","road":"苓雅區中正一路","building_type":"透天厝","total_floors":5.0,"transfer_floor_num":null,"age_years":0.0,"rooms":0.0,"halls":0.0,"baths":0.0,"building_area_sqm":964.84,"total_price":38000000,"unit_price_per_ping":130198.34222500001,"deal_date":"2026-01-05","region_p25":270218.171685,"price_ratio":0.48182674545209875},{"serial_no":"RPQNMLTKJHLGFAE18EA","district":"鹽埕區","address":"高雄市鹽埕區光榮街１０巷８號","road":"鹽埕區光榮街","building_type":"公寓(5樓含以下無電梯)","total_floors":5.0,"transfer_floor_num":1.0,"age_years":48.3,"rooms":1.0,"halls":1.0,"baths":1.0,"building_area_sqm":33.13,"total_price":470000,"unit_price_per_ping":46899.171795,"deal_date":"2026-01-09","region_p25":97229.74842,"price_ratio":0.48235414116687064},{"serial_no":"RPVOMLOLKHLGFCE58DA","district":"小港區","address":"高雄市小港區山田路２號","road":"小港區山田路","building_type":"透天厝","total_floors":4.0,"transfer_floor_num":null,"age_years":32.3,"rooms":6.0,"halls":2.0,"baths":4.0,"building_area_sqm":189.48,"total_price":5800000,"unit_price_per_ping":101190.07885,"deal_date":"2025-11-30","region_p25":209008.25662499998,"price_ratio":0.48414393040727566},{"serial_no":"RPQNMLMLJHLGFCE77EA","district":"前鎮區","address":"高雄市前鎮區新生路２４８之１２號四樓","road":"前鎮區新生路","building_type":"華廈(10層含以下有電梯)","total_floors":6.0,"transfer_floor_num":4.0,"age_years":31.9,"rooms":0.0,"halls":0.0,"baths":0.0,"building_area_sqm":2186.79,"total_price":55107360,"unit_price_per_ping":83305.782,"deal_date":"2026-01-14","region_p25":172012.39024375,"price_ratio":0.484301054603983},{"serial_no":"RPUNMLNLJHLGFJE88DA","district":"茄萣區","address":"高雄市茄萣區建業街１２２巷３號","road":"茄萣區建業街","building_type":"透天厝","total_floors":2.0,"transfer_floor_num":null,"age_years":34.2,"rooms":6.0,"halls":3.0,"baths":3.0,"building_area_sqm":180.12,"total_price":5000000,"unit_price_per_ping":91765.28581500001,"deal_date":"2025-12-18","region_p25":186544.62110375002,"price_ratio":0.49192137126249896},{"serial_no":"RPROMLKKKHLGFCE67DA","district":"前鎮區","address":"高雄市前鎮區佛西街３９號十樓","road":"前鎮區佛西街","building_type":"住宅大樓(11層含以上有電梯)","total_floors":12.0,"transfer_floor_num":10.0,"age_years":31.3,"rooms":3.0,"halls":2.0,"baths":2.0,"building_area_sqm":148.15,"total_price":5250000,"unit_price_per_ping":117147.10304500001,"deal_date":"2026-02-09","region_p25":235854.53661,"price_ratio":0.49669217615563593},{"serial_no":"RPXNMLOLKHLGFDE78DA","district":"三民區","address":"高雄市三民區民族一路８０號三十二樓之２","road":"三民區民族一路","building_type":"住宅大樓(11層含以上有電梯)","total_floors":50.0,"transfer_floor_num":30.0,"age_years":33.4,"rooms":0.0,"halls":0.0,"baths":0.0,"building_area_sqm":720.3900000000001,"total_price":25000000,"unit_price_per_ping":114720.65685500001,"deal_date":"2026-01-16","region_p25":227968.5864925,"price_ratio":0.5032301099905019},{"serial_no":"RPSNMLMJLHLGFLE88EA","district":"林園區","address":"高雄市林園區一心街３號三樓","road":"林園區一心街","building_type":"華廈(10層含以下有電梯)","total_floors":6.0,"transfer_floor_num":3.0,"age_years":32.2,"rooms":3.0,"halls":2.0,"baths":1.0,"building_area_sqm":87.27,"total_price":2500000,"unit_price_per_ping":94700.822895,"deal_date":"2026-03-02","region_p25":187998.3400575,"price_ratio":0.5037322290507215},{"serial_no":"RPRPMLMJKHLGFEE08DA","district":"左營區","address":"高雄市左營區左營大路４０１巷３６號","road":"左營區左營大路","building_type":"透天厝","total_floors":2.0,"transfer_floor_num":null,"age_years":57.9,"rooms":3.0,"halls":4.0,"baths":3.0,"building_area_sqm":97.34,"total_price":4100000,"unit_price_per_ping":139239.6642,"deal_date":"2026-01-08","region_p25":273622.30378874997,"price_ratio":0.5088754179465572},{"serial_no":"RPPNMLQLKIKGFAE97EA","district":"前金區","address":"高雄市前金區文武一街５２號三樓之３","road":"前金區文武一街","building_type":"華廈(10層含以下有電梯)","total_floors":7.0,"transfer_floor_num":3.0,"age_years":35.6,"rooms":1.0,"halls":0.0,"baths":1.0,"building_area_sqm":25.660000000000004,"total_price":700000,"unit_price_per_ping":90181.81480000001,"deal_date":"2025-12-08","region_p25":176412.39007875,"price_ratio":0.5111988719145129},{"serial_no":"RPUNMLMLJHLGFCE08DA","district":"小港區","address":"高雄市小港區宏平路６６０號十樓","road":"小港區宏平路","building_type":"住宅大樓(11層含以上有電梯)","total_floors":12.0,"transfer_floor_num":10.0,"age_years":34.9,"rooms":5.0,"halls":0.0,"baths":4.0,"building_area_sqm":189.11,"total_price":6200000,"unit_price_per_ping":108380.161225,"deal_date":"2025-12-25","region_p25":211280.15736625,"price_ratio":0.5129689535261237},{"serial_no":"RPSPMLTLKIKGFLE17DA","district":"林園區","address":"高雄市林園區力行路６７號","road":"林園區力行路","building_type":"透天厝","total_floors":2.0,"transfer_floor_num":null,"age_years":65.5,"rooms":2.0,"halls":1.0,"baths":1.0,"building_area_sqm":40.73,"total_price":856000,"unit_price_per_ping":69474.37756000001,"deal_date":"2025-12-29","region_p25":134211.565215,"price_ratio":0.5176482179364024},{"serial_no":"RPRPMLQKKIKGFEE58DA","district":"楠梓區","address":"高雄市楠梓區德祥路１５２巷２號十一樓之２","road":"楠梓區德祥路","building_type":"住宅大樓(11層含以上有電梯)","total_floors":13.0,"transfer_floor_num":11.0,"age_years":35.5,"rooms":4.0,"halls":2.0,"baths":2.0,"building_area_sqm":159.07,"total_price":6700000,"unit_price_per_ping":139239.6642,"deal_date":"2025-12-08","region_p25":268426.436215,"price_ratio":0.5187256000689664},{"serial_no":"RPROMLPKKIKGFLE09DA","district":"林園區","address":"高雄市林園區林家路１６２巷２６號","road":"林園區林家路","building_type":"透天厝","total_floors":4.0,"transfer_floor_num":null,"age_years":33.9,"rooms":4.0,"halls":2.0,"baths":3.0,"building_area_sqm":165.35,"total_price":3500000,"unit_price_per_ping":69973.551095,"deal_date":"2025-11-26","region_p25":134211.565215,"price_ratio":0.5213675213675214},{"serial_no":"RPSOMLTJKHLGFLE86DA","district":"大寮區","address":"高雄市大寮區鳳林路四段１６３號","road":"大寮區鳳林路四段","building_type":"透天厝","total_floors":4.0,"transfer_floor_num":null,"age_years":34.0,"rooms":5.0,"halls":2.0,"baths":4.0,"building_area_sqm":219.83,"total_price":5450000,"unit_price_per_ping":81957.02172,"deal_date":"2025-12-28","region_p25":157065.28336625,"price_ratio":0.5218022720456303},{"serial_no":"RPSNMLMKKHLGFCE87DA","district":"前鎮區","address":"高雄市前鎮區長江街９２號十四樓之２","road":"前鎮區長江街","building_type":"住宅大樓(11層含以上有電梯)","total_floors":24.0,"transfer_floor_num":14.0,"age_years":34.8,"rooms":4.0,"halls":2.0,"baths":2.0,"building_area_sqm":188.4,"total_price":7100000,"unit_price_per_ping":124581.81351,"deal_date":"2026-01-22","region_p25":235854.53661,"price_ratio":0.5282146160962072},{"serial_no":"RPUNMLSLJHLGFLE96DA","district":"林園區","address":"高雄市林園區椰樹東巷１３２號","road":null,"building_type":"透天厝","total_floors":3.0,"transfer_floor_num":null,"age_years":45.0,"rooms":0.0,"halls":0.0,"baths":0.0,"building_area_sqm":123.95,"total_price":2680000,"unit_price_per_ping":71477.68327000001,"deal_date":"2025-12-27","region_p25":134211.565215,"price_ratio":0.5325746939579793},{"serial_no":"RPQNMLSKLHLGFCE38DA","district":"前鎮區","address":"高雄市前鎮區育群街２５號九樓","road":"前鎮區育群街","building_type":"住宅大樓(11層含以上有電梯)","total_floors":15.0,"transfer_floor_num":9.0,"age_years":5.3,"rooms":3.0,"halls":2.0,"baths":2.0,"building_area_sqm":78.94,"total_price":3000000,"unit_price_per_ping":125633.05314,"deal_date":"2026-03-17","region_p25":235854.53661,"price_ratio":0.5326717685644605},{"serial_no":"RPPNMLMLKIKGFEE97EA","district":"楠梓區","address":"高雄市楠梓區新昌街１１１號","road":"楠梓區新昌街","building_type":"華廈(10層含以下有電梯)","total_floors":7.0,"transfer_floor_num":null,"age_years":34.9,"rooms":3.0,"halls":2.0,"baths":3.0,"building_area_sqm":362.68,"total_price":10000000,"unit_price_per_ping":91150.409805,"deal_date":"2025-12-16","region_p25":169555.36554250002,"price_ratio":0.5375849328823076},{"serial_no":"RPWNMLPLJHLGFFE88DA","district":"岡山區","address":"高雄市岡山區信中街１０５號　　　","road":"岡山區信中街","building_type":"透天厝","total_floors":3.0,"transfer_floor_num":null,"age_years":41.8,"rooms":5.0,"halls":2.0,"baths":2.0,"building_area_sqm":172.2,"total_price":6460000,"unit_price_per_ping":124016.524275,"deal_date":"2025-12-16","region_p25":230678.50374625,"price_ratio":0.537616302607113},{"serial_no":"RPXNMLRLJHLGFAE68DA","district":"鼓山區","address":"高雄市鼓山區美術東四路３６５號二十三樓","road":"鼓山區美術東四路","building_type":"住宅大樓(11層含以上有電梯)","total_floors":24.0,"transfer_floor_num":20.0,"age_years":11.9,"rooms":4.0,"halls":2.0,"baths":4.0,"building_area_sqm":248.76,"total_price":12316393,"unit_price_per_ping":163672.721135,"deal_date":"2026-01-09","region_p25":302720.64980500005,"price_ratio":0.540672468959191},{"serial_no":"RPSPMLPJJHLGFEE38DA","district":"楠梓區","address":"高雄市楠梓區南昌街３２巷４０號","road":"楠梓區南昌街","building_type":"透天厝","total_floors":2.0,"transfer_floor_num":null,"age_years":48.3,"rooms":6.0,"halls":2.0,"baths":5.0,"building_area_sqm":101.46,"total_price":4500000,"unit_price_per_ping":146618.17632,"deal_date":"2025-12-04","region_p25":269958.6675625,"price_ratio":0.5431134241542936},{"serial_no":"RPUOMLPJKHLGFBE28DA","district":"苓雅區","address":"高雄市苓雅區英明路１７３號５樓","road":"苓雅區英明路","building_type":"公寓(5樓含以下無電梯)","total_floors":5.0,"transfer_floor_num":5.0,"age_years":44.2,"rooms":2.0,"halls":2.0,"baths":2.0,"building_area_sqm":83.41,"total_price":1980000,"unit_price_per_ping":78472.72433000001,"deal_date":"2025-11-30","region_p25":144174.37475875003,"price_ratio":0.5442903738012393},{"serial_no":"RPOPMLPJKHLGFBE77DA","district":"苓雅區","address":"高雄市苓雅區建華街２３６號五樓","road":"苓雅區建華街","building_type":"公寓(5樓含以下無電梯)","total_floors":5.0,"transfer_floor_num":5.0,"age_years":44.2,"rooms":3.0,"halls":2.0,"baths":2.0,"building_area_sqm":109.85,"total_price":2620000,"unit_price_per_ping":78846.27803500001,"deal_date":"2025-11-30","region_p25":144174.37475875003,"price_ratio":0.5468813592355446},{"serial_no":"RPSNMLNJKHLGFAE67DA","district":"鼓山區","address":"高雄市鼓山區九如四路２０１１號十樓之１","road":"鼓山區九如四路","building_type":"住宅大樓(11層含以上有電梯)","total_floors":11.0,"transfer_floor_num":10.0,"age_years":43.5,"rooms":3.0,"halls":2.0,"baths":1.0,"building_area_sqm":82.63,"total_price":4160000,"unit_price_per_ping":166429.74582500002,"deal_date":"2026-01-31","region_p25":302720.64980500005,"price_ratio":0.5497799569742172},{"serial_no":"RPOOMLKMJHLGFCE47DA","district":"前鎮區","address":"高雄市前鎮區后平路８０號四樓之一","road":"前鎮區后平路","building_type":"住宅大樓(11層含以上有電梯)","total_floors":12.0,"transfer_floor_num":4.0,"age_years":32.3,"rooms":2.0,"halls":2.0,"baths":2.0,"building_area_sqm":136.88,"total_price":5380000,"unit_price_per_ping":129933.879425,"deal_date":"2026-01-01","region_p25":235854.53661,"price_ratio":0.550906848316654},{"serial_no":"RPQNMLSJJHLGFJE78DA","district":"阿蓮區","address":"高雄市阿蓮區中正路３３４號二樓之１","road":"阿蓮區中正路","building_type":"華廈(10層含以下有電梯)","total_floors":8.0,"transfer_floor_num":2.0,"age_years":32.6,"rooms":3.0,"halls":2.0,"baths":2.0,"building_area_sqm":94.89,"total_price":3800000,"unit_price_per_ping":132383.46611,"deal_date":"2026-01-04","region_p25":240033.04885000002,"price_ratio":0.5515218289491806},{"serial_no":"RPXPMLQLJHLGFEE56DA","district":"左營區","address":"高雄市左營區果峰街１９號十五樓","road":"左營區果峰街","building_type":"住宅大樓(11層含以上有電梯)","total_floors":18.0,"transfer_floor_num":15.0,"age_years":40.0,"rooms":3.0,"halls":2.0,"baths":2.0,"building_area_sqm":109.69,"total_price":4500000,"unit_price_per_ping":135619.829625,"deal_date":"2025-11-25","region_p25":245678.50318375003,"price_ratio":0.5520215560885522},{"serial_no":"RPWNMLKMKIKGFEE48DA","district":"左營區","address":"高雄市左營區果峰街２３號十五樓","road":"左營區果峰街","building_type":"住宅大樓(11層含以上有電梯)","total_floors":18.0,"transfer_floor_num":15.0,"age_years":39.9,"rooms":3.0,"halls":2.0,"baths":2.0,"building_area_sqm":109.69,"total_price":4500000,"unit_price_per_ping":135619.829625,"deal_date":"2025-11-05","region_p25":245678.50318375003,"price_ratio":0.5520215560885522},{"serial_no":"RPTNMLPJLHLGFBE18DA","district":"苓雅區","address":"高雄市苓雅區和平一路１８３號","road":"苓雅區和平一路","building_type":"透天厝","total_floors":3.0,"transfer_floor_num":null,"age_years":52.9,"rooms":3.0,"halls":1.0,"baths":3.0,"building_area_sqm":149.25,"total_price":6778006,"unit_price_per_ping":150128.91999,"deal_date":"2026-02-03","region_p25":270218.171685,"price_ratio":0.5555841010019451},{"serial_no":"RPXNMLLLJHLGFGE68DA","district":"鳳山區","address":"高雄市鳳山區五甲二路４５１巷５弄１４號","road":"鳳山區五甲二路","building_type":"透天厝","total_floors":4.0,"transfer_floor_num":null,"age_years":36.6,"rooms":3.0,"halls":2.0,"baths":4.0,"building_area_sqm":167.76000000000002,"total_price":6660000,"unit_price_per_ping":131239.6645,"deal_date":"2026-01-11","region_p25":235879.32999750003,"price_ratio":0.5563847603831626},{"serial_no":"RPPNMLKKMHLGFCE67EA","district":"前鎮區","address":"高雄市前鎮區鎮榮街７４之３號","road":"前鎮區鎮榮街","building_type":"公寓(5樓含以下無電梯)","total_floors":5.0,"transfer_floor_num":4.0,"age_years":44.3,"rooms":3.0,"halls":1.0,"baths":1.0,"building_area_sqm":57.95,"total_price":1350000,"unit_price_per_ping":77011.56736,"deal_date":"2026-03-18","region_p25":138047.9287075,"price_ratio":0.5578610855015027},{"serial_no":"RPPOMLNKJHLGFDE77DA","district":"三民區","address":"高雄市三民區皓東路５０號十一樓","road":"三民區皓東路","building_type":"住宅大樓(11層含以上有電梯)","total_floors":12.0,"transfer_floor_num":11.0,"age_years":35.4,"rooms":4.0,"halls":2.0,"baths":2.0,"building_area_sqm":227.93,"total_price":8780000,"unit_price_per_ping":127342.143985,"deal_date":"2025-12-05","region_p25":227968.5864925,"price_ratio":0.5585951377962747},{"serial_no":"RPWOMLKMKIKGFEE58DA","district":"左營區","address":"高雄市左營區果峰街２巷４號１０樓","road":"左營區果峰街","building_type":"住宅大樓(11層含以上有電梯)","total_floors":12.0,"transfer_floor_num":10.0,"age_years":40.1,"rooms":3.0,"halls":2.0,"baths":2.0,"building_area_sqm":108.15,"total_price":4500000,"unit_price_per_ping":137550.408065,"deal_date":"2025-12-28","region_p25":245678.50318375003,"price_ratio":0.5598797057230607},{"serial_no":"RPPNMLQKJHLGFEE08DA","district":"楠梓區","address":"高雄市楠梓區楠梓新路２８１號十八樓","road":"楠梓區楠梓新路","building_type":"住宅大樓(11層含以上有電梯)","total_floors":19.0,"transfer_floor_num":18.0,"age_years":31.5,"rooms":2.0,"halls":2.0,"baths":1.0,"building_area_sqm":98.44,"total_price":4500000,"unit_price_per_ping":151117.349705,"deal_date":"2025-12-18","region_p25":268426.436215,"price_ratio":0.5629749134841562},{"serial_no":"RPTNMLOLKIKGFFE58DA","district":"橋頭區","address":"高雄市橋頭區樹德路３０號七樓","road":"橋頭區樹德路","building_type":"住宅大樓(11層含以上有電梯)","total_floors":12.0,"transfer_floor_num":7.0,"age_years":31.8,"rooms":5.0,"halls":2.0,"baths":3.0,"building_area_sqm":219.25,"total_price":9130000,"unit_price_per_ping":137659.49897000002,"deal_date":"2025-12-20","region_p25":243533.875165,"price_ratio":0.5652581139963893},{"serial_no":"RPORMLOJKIKGFIE58DA","district":"仁武區","address":"高雄市仁武區綠園新村４２之１號","road":null,"building_type":"透天厝","total_floors":4.0,"transfer_floor_num":null,"age_years":27.2,"rooms":5.0,"halls":2.0,"baths":4.0,"building_area_sqm":268.35,"total_price":11000000,"unit_price_per_ping":135507.43293500002,"deal_date":"2025-11-13","region_p25":238818.1728625,"price_ratio":0.5674083814928886},{"serial_no":"RPWPMLMKJHLGFGE78DA","district":"鳳山區","address":"高雄市鳳山區中興街２號十二樓之２","road":"鳳山區中興街","building_type":"住宅大樓(11層含以上有電梯)","total_floors":13.0,"transfer_floor_num":10.0,"age_years":1.8,"rooms":2.0,"halls":2.0,"baths":3.0,"building_area_sqm":222.99,"total_price":11950000,"unit_price_per_ping":123874.37552,"deal_date":"2025-11-07","region_p25":217654.5372925,"price_ratio":0.569132980460355},{"serial_no":"RPPNMLNJJHLGFKE28DA","district":"美濃區","address":"高雄市美濃區自強街一段３５０巷２１弄１０號","road":"美濃區自強街一段","building_type":"透天厝","total_floors":4.0,"transfer_floor_num":null,"age_years":30.6,"rooms":6.0,"halls":2.0,"baths":4.0,"building_area_sqm":234.6,"total_price":4700000,"unit_price_per_ping":66228.09669,"deal_date":"2025-12-28","region_p25":115993.38408,"price_ratio":0.5709644322845417},{"serial_no":"RPPNMLMKJHLGFEE77EA","district":"楠梓區","address":"高雄市楠梓區常德路２４０巷２３弄３９號五樓","road":"楠梓區常德路","building_type":"住宅大樓(11層含以上有電梯)","total_floors":12.0,"transfer_floor_num":5.0,"age_years":31.9,"rooms":3.0,"halls":2.0,"baths":2.0,"building_area_sqm":113.99,"total_price":5300000,"unit_price_per_ping":153702.473575,"deal_date":"2025-12-21","region_p25":268426.436215,"price_ratio":0.5726055739602705},{"serial_no":"RPWNMLMLKIKGFJE09DA","district":"路竹區","address":"高雄市路竹區華光路１巷１弄２７號","road":"路竹區華光路","building_type":"透天厝","total_floors":3.0,"transfer_floor_num":null,"age_years":30.7,"rooms":5.0,"halls":2.0,"baths":3.0,"building_area_sqm":146.82,"total_price":4580000,"unit_price_per_ping":103123.963075,"deal_date":"2025-12-08","region_p25":179847.10069375002,"price_ratio":0.5733979734852837},{"serial_no":"RPPNMLPJKHLGFCE77DA","district":"小港區","address":"高雄市小港區高鳳路４４５號十四樓","road":"小港區高鳳路","building_type":"住宅大樓(11層含以上有電梯)","total_floors":19.0,"transfer_floor_num":14.0,"age_years":31.5,"rooms":4.0,"halls":2.0,"baths":2.0,"building_area_sqm":143.68,"total_price":5300000,"unit_price_per_ping":121943.79708,"deal_date":"2025-12-31","region_p25":211280.15736625,"price_ratio":0.5771663491740628},{"serial_no":"RPUNMLRJJHLGFDE48DA","district":"三民區","address":"高雄市三民區光裕路３３號四樓","road":"三民區光裕路","building_type":"公寓(5樓含以下無電梯)","total_floors":5.0,"transfer_floor_num":4.0,"age_years":41.6,"rooms":3.0,"halls":2.0,"baths":3.0,"building_area_sqm":96.36999999999999,"total_price":2500000,"unit_price_per_ping":85758.67447,"deal_date":"2025-11-26","region_p25":148305.7795625,"price_ratio":0.5782557815547505},{"serial_no":"RPTNMLKLJIKGFGE18DA","district":"鳳山區","address":"高雄市鳳山區建國路三段２８９號四樓","road":"鳳山區建國路三段","building_type":"住宅大樓(11層含以上有電梯)","total_floors":23.0,"transfer_floor_num":4.0,"age_years":31.2,"rooms":3.0,"halls":2.0,"baths":2.0,"building_area_sqm":148.85,"total_price":5680000,"unit_price_per_ping":126145.44981500001,"deal_date":"2025-11-20","region_p25":217654.5372925,"price_ratio":0.5795672876117284},{"serial_no":"RPPNMLNLKHLGFLE68DA","district":"林園區","address":"高雄市林園區海墘路６１巷１６號","road":"林園區海墘路","building_type":"透天厝","total_floors":4.0,"transfer_floor_num":null,"age_years":30.7,"rooms":6.0,"halls":2.0,"baths":4.0,"building_area_sqm":190.73,"total_price":4500000,"unit_price_per_ping":77996.69129,"deal_date":"2025-11-14","region_p25":134211.565215,"price_ratio":0.5811473188994802},{"serial_no":"RPPPMLNKJHLGFGE18DA","district":"大樹區","address":"高雄市大樹區竹寮路７之１５號","road":"大樹區竹寮路","building_type":"透天厝","total_floors":3.0,"transfer_floor_num":null,"age_years":33.2,"rooms":5.0,"halls":2.0,"baths":4.0,"building_area_sqm":264.62,"total_price":7000000,"unit_price_per_ping":87447.930605,"deal_date":"2025-12-19","region_p25":150198.34147500002,"price_ratio":0.5822163530318036},{"serial_no":"RPRNMLRKLHLGFFE68DA","district":"橋頭區","address":"高雄市橋頭區仕豐南路１００號六樓之６","road":"橋頭區仕豐南路","building_type":"住宅大樓(11層含以上有電梯)","total_floors":12.0,"transfer_floor_num":6.0,"age_years":31.8,"rooms":3.0,"halls":2.0,"baths":2.0,"building_area_sqm":116.11,"total_price":5000000,"unit_price_per_ping":142357.019455,"deal_date":"2026-03-15","region_p25":243533.875165,"price_ratio":0.584547095793346},{"serial_no":"RPQOMLQLKIKGFCE28DA","district":"小港區","address":"高雄市小港區光和路４０號三樓","road":"小港區光和路","building_type":"華廈(10層含以下有電梯)","total_floors":7.0,"transfer_floor_num":3.0,"age_years":28.7,"rooms":3.0,"halls":1.0,"baths":2.0,"building_area_sqm":114.46,"total_price":3250000,"unit_price_per_ping":93864.45929,"deal_date":"2025-11-28","region_p25":160266.93613875,"price_ratio":0.5856757579039104}]